sdm_ore_shard01/__init__.py
sdm_ore_shard01/shard-01.bin
sdm_ore_shard01-0.1.0.dist-info/METADATA
sdm_ore_shard01-0.1.0.dist-info/WHEEL
sdm_ore_shard01-0.1.0.dist-info/top_level.txt
sdm_ore_shard01-0.1.0.dist-info/RECORD
