Metadata-Version: 2.4
Name: sdm-ore-shard01
Version: 0.1.0
Summary: Shard 01 for sdm-ore
Author: OREYH
Requires-Python: >=3.8
